sigma/backends/carbonblack/__init__.py
sigma/backends/carbonblack/carbonblack.py
sigma/pipelines/carbonblack/__init__.py
sigma/pipelines/carbonblack/carbonblack.py
pysigma_backend_carbonblack-0.1.8.dist-info/LICENSE
pysigma_backend_carbonblack-0.1.8.dist-info/METADATA
pysigma_backend_carbonblack-0.1.8.dist-info/WHEEL
pysigma_backend_carbonblack-0.1.8.dist-info/RECORD
