Metadata-Version: 2.1
Name: pysigma-backend-carbonblack
Version: 0.1.8
Summary: pySigma carbonblack backend
Home-page: https://github.com/7RedViolin/pySigma-backend-carbonblack
License: MIT
Author: Cori Smith
Author-email: cs2718281@gmail.com
Requires-Python: >=3.8,<4.0
Classifier: License :: OSI Approved :: MIT License
Classifier: Programming Language :: Python :: 3
Classifier: Programming Language :: Python :: 3.8
Classifier: Programming Language :: Python :: 3.9
Classifier: Programming Language :: Python :: 3.10
Classifier: Programming Language :: Python :: 3.11
Requires-Dist: pysigma (>=0.9.6)
Project-URL: Repository, https://github.com/7RedViolin/pySigma-backend-carbonblack
